zeroth_normalizer/__init__.py
zeroth_normalizer/version.py
zeroth_normalizer/normalizer/__init__.py
zeroth_normalizer/normalizer/at_unicode.py
zeroth_normalizer/normalizer/step1.py
zeroth_normalizer/normalizer/step2.py
zeroth_normalizer/normalizer/step3.py
zeroth_normalizer/normalizer/step4.py
zeroth_normalizer-0.1.0.dist-info/METADATA
zeroth_normalizer-0.1.0.dist-info/WHEEL
zeroth_normalizer-0.1.0.dist-info/top_level.txt
zeroth_normalizer-0.1.0.dist-info/RECORD
