Metadata-Version: 2.1
Name: zeroth-normalizer
Version: 0.1.0
Summary: zeroth korean text normalizer
Home-page: https://github.com/drowsy-probius/zeroth-normalizer
Author: drowsy-probius
Author-email: k123s456h@gmail.com
License: MIT
Keywords: natural language processor,normalizer,zeroth,korean,text normalizer,korean text,korean language
Classifier: Programming Language :: Python :: 3.8
Classifier: Operating System :: OS Independent
Requires-Python: >=3.8
Requires-Dist: requests
